[

{
  "file": "https://2017services.s3.amazonaws.com/Retreat/December/1001.mp4",
  "image": "https://2017services.s3.amazonaws.com/Retreat/December/dler17.jpg",
  "title": "1001 Blessings",
  "mediaid": "wc_00001"
},

{
  "file": "https://2018services.s3.amazonaws.com/MBS/MBS01012018%28HQ%29The_Master%27s_Call_To_Renewal_Me.mp4",
  "image": "http://2018services.s3.amazonaws.com/OTHERS/images/poster/MBSHD.jpg",
  "title": "The Master's Call to Renewal",
  "mediaid": "wc_mbs_00002"
},

{
  "file": "https://2018services.s3.amazonaws.com/SWS/SWS07012018%28HQ%29A_New_Dawn_with_Great_Reformers_Restorers_Me.mp4",
  "image": "http://2018services.s3.amazonaws.com/OTHERS/images/poster/SWSHD.JPG",
  "title": "A New Dawn with Great Reformers and Restorers",
  "mediaid": "wc_sws_00003"
},

{
  "file": "https://2018services.s3.amazonaws.com/MBS/MBS08012018%28HQ%29Believing_and_Following_The_True_Shepherd_Me.mp4",
  "image": "http://2018services.s3.amazonaws.com/OTHERS/images/poster/MBSHD.jpg",
  "title": "Believing and Following the True Shepherd",
  "mediaid": "wc_mbs_00004"
},

{
  "file": "https://2018services.s3.amazonaws.com/TLM/TLM09012018%28HQ%29The_Sheep%27s_Conquering_Mission_among_Wolves_Me.mp4",
  "image": "http://2018services.s3.amazonaws.com/OTHERS/images/poster/TLMHD.jpg",
  "title": "The Sheep's Conquering Mission Among Wolves",
  "mediaid": "wc_tlm_00005"
},

{
  "file": "https://2018services.s3.amazonaws.com/SWM/SWM13012018%28HQ%29THE_POWERFUL_LIFE_OF_FAITH_AND_FREEDOM_Me.mp4",
  "image": "http://2018services.s3.amazonaws.com/OTHERS/images/poster/SWTHD.jpg",
  "title": "The Powerful Life of Faith and Freedom",
  "mediaid": "wc_swt_00006"
},

{
  "file": "https://2018services.s3.amazonaws.com/SWS/SWS140118%28HQ%29Renewed_Strength_for_the_Heavenward_Journey_Me.mp4",
  "image": "http://2018services.s3.amazonaws.com/OTHERS/images/poster/SWSHD.jpg",
  "title": "Renewed Strength for the Heavenward Journey",
  "mediaid": "wc_sws_00007"
},

{
  "file": "https://2018services.s3.amazonaws.com/MBS/MBS150118%28HQ%29_MAN%27S_SICKNESS_THAT_EVENTUALLY_RESULTED_IN_GOD%27S_GLORY_Me.mp4",
  "image": "http://2018services.s3.amazonaws.com/OTHERS/images/poster/MBSHD.jpg",
  "title": "Man's Sickness that Eventually Resulted In God's Glory",
  "mediaid": "wc_sws_00008"
},

{
  "file": "https://2018services.s3.amazonaws.com/SWS/SWS21012018%28HQ%29Walking_in_the_Old_Path_with_New_Strength_Me.mp4",
  "image": "http://2018services.s3.amazonaws.com/OTHERS/images/poster/SWSHD.jpg",
  "title": "Walking In the Old Path with New Strength",
  "mediaid": "wc_sws_00009"
},

{
  "file": "https://2018services.s3.amazonaws.com/MBS/MBS22012018%28HQ%29CHRIST%27S_POWER_OVER_SIN_AND_SUFFERING_Me.mp4",
  "image": "http://2018services.s3.amazonaws.com/OTHERS/images/poster/MBSHD.jpg",
  "title": "Christ's Power Over Sin and Suffering",
  "mediaid": "wc_sws_00010"
}

]